{
  "name": "ArtNet for Java and Processing",
  "categories": [
    "Data"
  ],
  "authors": [
    "[Florian Bruggisser](https://bildspur.ch)"
  ],
  "url": "https://github.com/cansik/artnet4j",
  "sentence": "Framework for sending and receiving DMX data over the ArtNet protocol.",
  "paragraph": "Send and receive DMX data over the ArtNet protocol.",
  "id": "230",
  "type": "library",
  "packages": [
    {
      "mode": "java",
      "minRevision": "0",
      "maxRevision": "0",
      "props": "https://github.com/cansik/artnet4j/releases/download/latest/artnet4j.txt",
      "download": "https://github.com/cansik/artnet4j/releases/download/latest/artnet4j.zip"
    }
  ]
}