{
  "name": "Getting Started",
  "authors": [
    "[Jae Hyun](http://www.github.com/jaewhyun)"
  ],
  "url": "http://www.github.com/jaewhyun/GettingStarted",
  "categories": null,
  "sentence": "A Tool that provides a quick introduction to the PDE for new/beginner users.",
  "paragraph": "",
  "id": "233",
  "type": "tool",
  "packages": [
    {
      "mode": "java",
      "minRevision": "228",
      "maxRevision": "0",
      "props": "https://github.com/jaewhyun/GettingStarted/releases/download/latest/GettingStarted.txt",
      "download": "https://github.com/jaewhyun/GettingStarted/releases/download/latest/GettingStarted.zip"
    }
  ]
}