{
  "name": "nyar4psg",
  "authors": ["[R.Iizuka](http://nyatla.jp)"],
  "url": "https://github.com/nyatla/NyARToolkit-for-Processing/",
  "categories": ["Video & Vision"],
  "sentence": "NyARToolkit for proce55ing(NyAR4psg) is front-end of NyARToolkit for Java. This library can easily make the AR application.",
  "paragraph": "This library requires a web camera to make AR view.",
  "type": "library",
  "packages": [
    {
      "mode": "java",
      "minRevision": "227",
      "maxRevision": "0",
      "props": "https://github.com/nyatla/NyARToolkit-for-Processing/releases/download/latest/nyar4psg.txt",
      "download": "https://github.com/nyatla/NyARToolkit-for-Processing/releases/download/latest/nyar4psg.zip"
    }
  ]
}
